MyLlmUtils/__init__.py
MyLlmUtils/commons.py
MyLlmUtils/config.ini
MyLlmUtils/llm_definition.py
myllmutils-0.1.5.dist-info/LICENSE
myllmutils-0.1.5.dist-info/LICENSE.txt
myllmutils-0.1.5.dist-info/METADATA
myllmutils-0.1.5.dist-info/WHEEL
myllmutils-0.1.5.dist-info/RECORD
