Metadata-Version: 2.1
Name: myllmutils
Version: 0.1.5
Summary: 
Author: Ken Hu
Author-email: ken.hu@hwacom.com
Requires-Python: >=3.9,<4.0
Classifier: Programming Language :: Python :: 3
Classifier: Programming Language :: Python :: 3.9
Classifier: Programming Language :: Python :: 3.10
Classifier: Programming Language :: Python :: 3.11
Requires-Dist: langchain (>=0.1.5,<0.2.0)
Requires-Dist: langchain-community (>=0.0.17,<0.0.18)
Requires-Dist: langchain-openai (>=0.0.5,<0.0.6)
Requires-Dist: pytest (>=8.0.0,<9.0.0)
